PyD3XX/FTD3XX.dll
PyD3XX/FTD3XXWU.dll
PyD3XX/FTD3XXWU_32.dll
PyD3XX/FTD3XXWU_ARM.dll
PyD3XX/FTD3XX_32.dll
PyD3XX/PyD3XX.py
PyD3XX/__init__.py
PyD3XX/libftd3xx.dylib
PyD3XX/libftd3xx.so
PyD3XX/libftd3xx_32.dylib
PyD3XX/libftd3xx_32.so
PyD3XX/libftd3xx_ARM.dylib
PyD3XX/libftd3xx_ARM.so
PyD3XX/libftd3xx_ARM_32.so
pyd3xx-1.0.8.dist-info/METADATA
pyd3xx-1.0.8.dist-info/WHEEL
pyd3xx-1.0.8.dist-info/entry_points.txt
pyd3xx-1.0.8.dist-info/licenses/LICENSE
pyd3xx-1.0.8.dist-info/RECORD
