Metadata-Version: 2.1
Name: PyD3XX
Version: 1.0.8
Summary: A Python wrapper for the FTDI D3XX library.
Keywords: FTDI,ftdichip,PyD3XX,D3XX,FTD3XX,FT600,FT601
Author-Email: Hector Soto <hector.soto@ftdichip.com>
Classifier: Programming Language :: Python :: 3
Classifier: License :: OSI Approved :: MIT License
Classifier: Operating System :: OS Independent
Project-URL: GitHub_Repo, https://github.com/S-Hector/PyD3XX
Project-URL: FTDI_Homepage, https://ftdichip.com/
Project-URL: FTDI_D3XX_Drivers, https://ftdichip.com/drivers/d3xx-drivers/
Project-URL: D3XX_Programming_Guide, https://ftdichip.com/wp-content/uploads/2020/08/AN_379-D3xx-Programmers-Guide-1.pdf
Requires-Python: >=3.10
